LICENSE.txt
MANIFEST.in
README.md
setup.py
hyaline/__init__.py
hyaline/meta.py
hyaline.egg-info/PKG-INFO
hyaline.egg-info/SOURCES.txt
hyaline.egg-info/dependency_links.txt
hyaline.egg-info/requires.txt
hyaline.egg-info/top_level.txt
hyaline/errors/ChannelErrors.py
hyaline/errors/GuildErrors.py
hyaline/errors/MessageErrors.py
hyaline/errors/SessionErrors.py
hyaline/errors/WebhookErrors.py
hyaline/errors/__init__.py
hyaline/helpers/ActivityFlags.py
hyaline/helpers/Image.py
hyaline/helpers/Intents.py
hyaline/helpers/Permissions.py
hyaline/helpers/Types.py
hyaline/helpers/__init__.py
hyaline/managers/BaseClient.py
hyaline/managers/__init__.py
hyaline/models/Activity.py
hyaline/models/Application.py
hyaline/models/Attachment.py
hyaline/models/AuditLog.py
hyaline/models/Ban.py
hyaline/models/Channel.py
hyaline/models/ClientUser.py
hyaline/models/Embed.py
hyaline/models/Emoji.py
hyaline/models/Guild.py
hyaline/models/GuildPreview.py
hyaline/models/Invite.py
hyaline/models/Member.py
hyaline/models/Message.py
hyaline/models/MessageActivity.py
hyaline/models/MessageReference.py
hyaline/models/Overwrite.py
hyaline/models/PresenceUpdate.py
hyaline/models/Reaction.py
hyaline/models/Role.py
hyaline/models/RoleTags.py
hyaline/models/Sticker.py
hyaline/models/Team.py
hyaline/models/TeamMember.py
hyaline/models/ThreadMember.py
hyaline/models/ThreadMetadata.py
hyaline/models/User.py
hyaline/models/VoiceState.py
hyaline/models/Webhook.py
hyaline/models/__init__.py
hyaline/utils/Dict2Query.py
hyaline/utils/Request.py
hyaline/utils/WrongType.py
hyaline/utils/__init__.py