Metadata-Version: 2.1
Name: hyaline
Version: 0.1.2
Summary: Discord API Wrapper for Python!
Home-page: https://github.com/5elenay/hyaline/
Author: 5elenay
Author-email: 
License: MIT
Project-URL: Bug Tracker, https://github.com/5elenay/hyaline/issues
Keywords: discord,wrapper,api,gateway,lightweight,discord-api
Platform: UNKNOWN
Classifier: Development Status :: 4 - Beta
Classifier: Intended Audience :: Developers
Classifier: Operating System :: OS Independent
Classifier: License :: OSI Approved :: MIT License
Classifier: Programming Language :: Python :: 3
Requires-Python: >=3.6.0
